README.md
setup.py
csvtsdb/__init__.py
csvtsdb/__main__.py
csvtsdb/csvtsdb.py
csvtsdb.egg-info/PKG-INFO
csvtsdb.egg-info/SOURCES.txt
csvtsdb.egg-info/dependency_links.txt
csvtsdb.egg-info/requires.txt
csvtsdb.egg-info/top_level.txt