Metadata-Version: 1.0
Name: csvtsdb
Version: 0.1.6
Summary: CSV-backed timeseries database usable standalone or as a Twisted resource
Home-page: http://github.com/anotherkamila/csvtsdb
Author: Kamila Součková
Author-email: kamisouckova@gmail.com
License: MIT
Platform: UNKNOWN
